{"id": 17134, "annotations": [{"id": 17237, "completed_by": 2, "result": [{"type": "labels", "value": {"end": 9, "text": "Operator", "start": 0, "labels": ["OPERATOR"]}, "origin": "manual", "to_name": "text", "from_name": "label-intro"}, {"type": "labels", "value": {"end": 126, "text": ": Thank you. Our next question comes from the line of Brendan Barnicle with Pacific Crest Securities. Please proceed.", "start": 10, "labels": ["INTRO"]}, "origin": "manual", "to_name": "text", "from_name": "label-intro"}, {"type": "labels", "value": {"end": 143, "text": "Brendan Barnicle", "start": 126, "labels": ["ANALYST"]}, "origin": "manual", "to_name": "text", "from_name": "label-intro"}, {"type": "labels", "value": {"end": 563, "text": ": Thanks so much. Amy, when we first started talking about Office 365, I think at that time, you were suggesting that the move from an Office CAL to an Office 365 license would increase gross profit by about 50%. Now that you had a couple of quarters with Office 365, do you think those changes to the model still make sense and more importantly, are there may be other changes that you're seeing that are more accurate?", "start": 144, "labels": ["QUESTION"]}, "origin": "manual", "to_name": "text", "from_name": "label-intro"}, {"type": "labels", "value": {"end": 572, "text": "Amy Hood", "start": 563, "labels": ["REPRESENTATIVE"]}, "origin": "manual", "to_name": "text", "from_name": "label-intro"}, {"type": "labels", "value": {"end": 2137, "text": ": Thanks for the question. In general, I think we're still on the early ends of seeing the opportunity that we have in that segment. As you pointed out, there is a couple components that make gross profit dollars per seat or the life time value of a customer depending on the terms you want to use improve and increase over the life cycle. The very first thing and I think Satya even mentioned it in its most direct in SMB is moving from buying a copy of Office, which was a very static concept to the idea where you could buy Office and frankly get all the benefits that those who used to deploy servers used to get only with IT departments of their own. So as you move Office, it\u2019s simply the first step. So, even though obviously it comes at a little lower gross margin percentage, our ability to add workloads, add premium services and to increase our overall footprint inside a customer is really where the life time value goes up. And frankly over time and watching, I think both the creativity and the pace of innovation we\u2019ve seen coming out of our engineering teams particularly in Azure and Office 365 and our CRM team online, I actually even have more confidence in our ability to attach and grow that gross profit over time. We mentioned simply one that didn\u2019t exist I think Brendan when we first started having this conversation, which was our EMS suite and I look and say, those opportunities as well as the creativity of our people I think gives me more confidence if not less in the structural integrity of the lifetime value of a customer argument.", "start": 573, "labels": ["ANSWER"]}, "origin": "manual", "to_name": "text", "from_name": "label-intro"}, {"type": "labels", "value": {"end": 2154, "text": "Brendan Barnicle", "start": 2137, "labels": ["ANALYST"]}, "origin": "manual", "to_name": "text", "from_name": "label-intro"}, {"type": "labels", "value": {"end": 2181, "text": ": Great. Thank you so much.", "start": 2155, "labels": ["QUESTION"]}, "origin": "manual", "to_name": "text", "from_name": "label-intro"}, {"type": "labels", "value": {"end": 2191, "text": "Chris Suh", "start": 2181, "labels": ["REPRESENTATIVE"]}, "origin": "manual", "to_name": "text", "from_name": "label-intro"}, {"type": "labels", "value": {"end": 2258, "text": ": Thanks. Operator, we will have time for one last question please.", "start": 2192, "labels": ["ANSWER"]}, "origin": "manual", "to_name": "text", "from_name": "label-intro"}], "was_cancelled": false, "ground_truth": true, "created_at": "2022-02-04T10:03:51.589333Z", "updated_at": "2022-02-04T10:03:51.589338Z", "lead_time": null, "prediction": {}, "result_count": 0, "task": 17134, "parent_prediction": null, "parent_annotation": null}], "data": {"year": 2015, "company": "MSFT", "my_text": "\nOperator: Thank you. Our next question comes from the line of Brendan Barnicle with Pacific Crest Securities. Please proceed.\nBrendan Barnicle: Thanks so much. Amy, when we first started talking about Office 365, I think at that time, you were suggesting that the move from an Office CAL to an Office 365 license would increase gross profit by about 50%. Now that you had a couple of quarters with Office 365, do you think those changes to the model still make sense and more importantly, are there may be other changes that you're seeing that are more accurate?\nAmy Hood: Thanks for the question. In general, I think we're still on the early ends of seeing the opportunity that we have in that segment. As you pointed out, there is a couple components that make gross profit dollars per seat or the life time value of a customer depending on the terms you want to use improve and increase over the life cycle. The very first thing and I think Satya even mentioned it in its most direct in SMB is moving from buying a copy of Office, which was a very static concept to the idea where you could buy Office and frankly get all the benefits that those who used to deploy servers used to get only with IT departments of their own. So as you move Office, it\u2019s simply the first step. So, even though obviously it comes at a little lower gross margin percentage, our ability to add workloads, add premium services and to increase our overall footprint inside a customer is really where the life time value goes up. And frankly over time and watching, I think both the creativity and the pace of innovation we\u2019ve seen coming out of our engineering teams particularly in Azure and Office 365 and our CRM team online, I actually even have more confidence in our ability to attach and grow that gross profit over time. We mentioned simply one that didn\u2019t exist I think Brendan when we first started having this conversation, which was our EMS suite and I look and say, those opportunities as well as the creativity of our people I think gives me more confidence if not less in the structural integrity of the lifetime value of a customer argument.\nBrendan Barnicle: Great. Thank you so much.\nChris Suh: Thanks. Operator, we will have time for one last question please.", "quarter": 2}}